whitebox_plugin_icons/__init__.py
whitebox_plugin_icons/jsx/Logo.jsx
whitebox_plugin_icons/jsx/assets/icons/add.svg
whitebox_plugin_icons/jsx/assets/icons/airplane.svg
whitebox_plugin_icons/jsx/assets/icons/arrow_back.svg
whitebox_plugin_icons/jsx/assets/icons/arrow_circle_up.svg
whitebox_plugin_icons/jsx/assets/icons/arrow_forward.svg
whitebox_plugin_icons/jsx/assets/icons/calendar.svg
whitebox_plugin_icons/jsx/assets/icons/camera_device.svg
whitebox_plugin_icons/jsx/assets/icons/camera_roll.svg
whitebox_plugin_icons/jsx/assets/icons/cancel.svg
whitebox_plugin_icons/jsx/assets/icons/chat.svg
whitebox_plugin_icons/jsx/assets/icons/check_circle.svg
whitebox_plugin_icons/jsx/assets/icons/chevron_down.svg
whitebox_plugin_icons/jsx/assets/icons/chevron_right.svg
whitebox_plugin_icons/jsx/assets/icons/chevron_up.svg
whitebox_plugin_icons/jsx/assets/icons/close.svg
whitebox_plugin_icons/jsx/assets/icons/drag_indicator.svg
whitebox_plugin_icons/jsx/assets/icons/eclipse.svg
whitebox_plugin_icons/jsx/assets/icons/edit.svg
whitebox_plugin_icons/jsx/assets/icons/expand_less.svg
whitebox_plugin_icons/jsx/assets/icons/eye.svg
whitebox_plugin_icons/jsx/assets/icons/flight_land.svg
whitebox_plugin_icons/jsx/assets/icons/flight_takeoff.svg
whitebox_plugin_icons/jsx/assets/icons/fullscreen_exit.svg
whitebox_plugin_icons/jsx/assets/icons/import_export.svg
whitebox_plugin_icons/jsx/assets/icons/info.svg
whitebox_plugin_icons/jsx/assets/icons/link.svg
whitebox_plugin_icons/jsx/assets/icons/location_on.svg
whitebox_plugin_icons/jsx/assets/icons/location_target.svg
whitebox_plugin_icons/jsx/assets/icons/play.svg
whitebox_plugin_icons/jsx/assets/icons/play_circle.svg
whitebox_plugin_icons/jsx/assets/icons/restart.svg
whitebox_plugin_icons/jsx/assets/icons/search.svg
whitebox_plugin_icons/jsx/assets/icons/share.svg
whitebox_plugin_icons/jsx/assets/icons/spinner.svg
whitebox_plugin_icons/jsx/assets/icons/stop_circle.svg
whitebox_plugin_icons/jsx/assets/icons/trash.svg
whitebox_plugin_icons-0.1.7.dist-info/LICENSE
whitebox_plugin_icons-0.1.7.dist-info/METADATA
whitebox_plugin_icons-0.1.7.dist-info/WHEEL
whitebox_plugin_icons-0.1.7.dist-info/RECORD
